odoo/addons/l10n_it_fatturapa_in_purchase/README.rst
odoo/addons/l10n_it_fatturapa_in_purchase/__init__.py
odoo/addons/l10n_it_fatturapa_in_purchase/__manifest__.py
odoo/addons/l10n_it_fatturapa_in_purchase/i18n/it.po
odoo/addons/l10n_it_fatturapa_in_purchase/i18n/l10n_it_fatturapa_in_purchase.pot
odoo/addons/l10n_it_fatturapa_in_purchase/models/__init__.py
odoo/addons/l10n_it_fatturapa_in_purchase/models/purchase_order.py
odoo/addons/l10n_it_fatturapa_in_purchase/readme/CONTRIBUTORS.rst
odoo/addons/l10n_it_fatturapa_in_purchase/readme/DESCRIPTION.rst
odoo/addons/l10n_it_fatturapa_in_purchase/readme/USAGE.rst
odoo/addons/l10n_it_fatturapa_in_purchase/static/description/icon.png
odoo/addons/l10n_it_fatturapa_in_purchase/static/description/index.html
odoo/addons/l10n_it_fatturapa_in_purchase/tests/__init__.py
odoo/addons/l10n_it_fatturapa_in_purchase/tests/test_l10n_it_fatturapa_in_purchase.py
odoo/addons/l10n_it_fatturapa_in_purchase/tests/data/IT05979361218_008.xml
odoo/addons/l10n_it_fatturapa_in_purchase/views/invoice_view.xml
odoo12_addon_l10n_it_fatturapa_in_purchase-12.0.1.0.2.dist-info/METADATA
odoo12_addon_l10n_it_fatturapa_in_purchase-12.0.1.0.2.dist-info/WHEEL
odoo12_addon_l10n_it_fatturapa_in_purchase-12.0.1.0.2.dist-info/top_level.txt
odoo12_addon_l10n_it_fatturapa_in_purchase-12.0.1.0.2.dist-info/RECORD
