Metadata-Version: 2.1
Name: odoo12-addon-l10n-it-fatturapa-in-purchase
Version: 12.0.1.0.2
Summary: Modulo ponte tra ricezione fatture elettroniche e acquisti
Home-page: https://github.com/OCA/l10n-italy/tree/12.0/l10n_it_fatturapa_in_purchase
Author: Agile Business Group, Odoo Community Association (OCA)
Author-email: support@odoo-community.org
License: AGPL-3
Platform: UNKNOWN
Classifier: Programming Language :: Python
Classifier: Framework :: Odoo
Classifier: License :: OSI Approved :: GNU Affero General Public License v3
Requires-Python: >=3.5
Requires-Dist: odoo12-addon-l10n-it-fatturapa-in
Requires-Dist: odoo (<12.1dev,>=12.0a)
